setup.py
barkas62_distributions/Binomialdistribution.py
barkas62_distributions/Gaussiandistribution.py
barkas62_distributions/Generaldistribution.py
barkas62_distributions/__init__.py
barkas62_distributions.egg-info/PKG-INFO
barkas62_distributions.egg-info/SOURCES.txt
barkas62_distributions.egg-info/dependency_links.txt
barkas62_distributions.egg-info/not-zip-safe
barkas62_distributions.egg-info/top_level.txt