Metadata-Version: 1.0
Name: barkas62-distributions
Version: 0.1
Summary: Gaussian ans Binomial distributions
Home-page: UNKNOWN
Author: Boris Gorbatov
Author-email: UNKNOWN
License: UNKNOWN
Platform: UNKNOWN
